texifast/__init__.py
texifast/config.py
texifast/helpers.py
texifast/model.py
texifast/pipeline.py
texifast-0.1.3.dist-info/LICENSE
texifast-0.1.3.dist-info/METADATA
texifast-0.1.3.dist-info/WHEEL
texifast-0.1.3.dist-info/top_level.txt
texifast-0.1.3.dist-info/RECORD
