Metadata-Version: 2.1
Name: texifast
Version: 0.1.3
Summary: LaTeX and markdown OCR powered by texify, without bloated dependencies like torch or transformers.
Author-email: Spedon <hi@sped0n.com>
Requires-Python: <=3.12,>=3.9
License-File: LICENSE
Requires-Dist: numpy >=1.26
Requires-Dist: pillow >=10
Requires-Dist: tokenizers >=0.20
Provides-Extra: cpu
Requires-Dist: onnxruntime >=1.19.0 ; extra == 'cpu'
Provides-Extra: gpu
Requires-Dist: onnxruntime-gpu >=1.19.0 ; extra == 'gpu'
